smilecoin/__init__.py
smilecoin/api.py
smilecoin-1.3.0.dist-info/LICENSE
smilecoin-1.3.0.dist-info/METADATA
smilecoin-1.3.0.dist-info/WHEEL
smilecoin-1.3.0.dist-info/top_level.txt
smilecoin-1.3.0.dist-info/RECORD
