Metadata-Version: 2.1
Name: smilecoin
Version: 1.3.0
Summary: Smile Coin Python SDK
Home-page: https://github.com/SmileCoinUS/smilecoin-sdk
Author: Nick Bucheleres
Author-email: nick@smilecoin.us
Project-URL: Bug Tracker, https://github.com/SmileCoinUS/smilecoin-sdk
Project-URL: Documentation, https://docs.smilecoin.us
Classifier: Programming Language :: Python :: 3
Classifier: License :: OSI Approved :: MIT License
Classifier: Operating System :: OS Independent
Requires-Python: >=3.6
License-File: LICENSE
Requires-Dist: requests
